ttkbootstrap/__init__.py
ttkbootstrap/__main__.py
ttkbootstrap/constants.py
ttkbootstrap/dialogs.py
ttkbootstrap/icons.py
ttkbootstrap/publisher.py
ttkbootstrap/scrolled.py
ttkbootstrap/style.py
ttkbootstrap/tableview.py
ttkbootstrap/toast.py
ttkbootstrap/tooltip.py
ttkbootstrap/utility.py
ttkbootstrap/validation.py
ttkbootstrap/widgets.py
ttkbootstrap/window.py
ttkbootstrap/themes/__init__.py
ttkbootstrap/themes/standard.py
ttkbootstrap/themes/user.py
ttkcreator/__init__.py
ttkcreator/__main__.py
ttkbootstrap_fork_laggykiller-1.5.1.post1.dist-info/LICENSE
ttkbootstrap_fork_laggykiller-1.5.1.post1.dist-info/METADATA
ttkbootstrap_fork_laggykiller-1.5.1.post1.dist-info/WHEEL
ttkbootstrap_fork_laggykiller-1.5.1.post1.dist-info/top_level.txt
ttkbootstrap_fork_laggykiller-1.5.1.post1.dist-info/RECORD
