Metadata-Version: 2.1
Name: ttkbootstrap-fork-laggykiller
Version: 1.5.1.post1
Summary: A fork of ttkbootstrap for personal use
Home-page: https://github.com/israel-dryer/ttkbootstrap
Author: Israel Dryer
Author-email: israel.dryer@gmail.com
Classifier: Programming Language :: Python :: 3
Classifier: License :: OSI Approved :: MIT License
Classifier: Operating System :: OS Independent
Requires-Python: >=3.7
License-File: LICENSE
Requires-Dist: pillow >=8.2.0
